kontur/unp1c/__init__.py
kontur/unp1c/helpers.py
kontur/unp1c/tools/v8file.py
kontur/unp1c/tools/v8form.py
kontur_unp1c-0.0.0.dist-info/METADATA
kontur_unp1c-0.0.0.dist-info/WHEEL
kontur_unp1c-0.0.0.dist-info/top_level.txt
kontur_unp1c-0.0.0.dist-info/RECORD
