Metadata-Version: 2.1
Name: kontur-unp1c
Version: 0.0.0
Summary: Сбор/разбор бинарей 1С:Предприятие
Home-page: https://git.skbkontur.ru/python-libs/unp1c
Author: korotovskih
Author-email: korotovskih@kontur.ru
Maintainer: korotovskih
Maintainer-email: korotovskih@kontur.ru
License: UNKNOWN
Platform: UNKNOWN
Classifier: Programming Language :: Python :: 3.6
Classifier: Programming Language :: Python :: 3.7
Classifier: Programming Language :: Python :: 3.8
Classifier: Programming Language :: Python :: 3.9
Classifier: Programming Language :: Python :: 3.10
Classifier: Operating System :: OS Independent
Requires-Python: >=3.6
Requires-Dist: dataclasses ; python_version < "3.7"
